hgcroc_toa_simulator/__init__.py
hgcroc_toa_simulator/cli.py
hgcroc_toa_simulator/plot_toa_timing_test.py
hgcroc_toa_simulator/tests.py
hgcroc_toa_simulator/toa.py
hgcroc_toa_simulator/utils.py
hgcroc_toa_simulator-0.4.5.dist-info/LICENSE.rst
hgcroc_toa_simulator-0.4.5.dist-info/METADATA
hgcroc_toa_simulator-0.4.5.dist-info/WHEEL
hgcroc_toa_simulator-0.4.5.dist-info/entry_points.txt
hgcroc_toa_simulator-0.4.5.dist-info/top_level.txt
hgcroc_toa_simulator-0.4.5.dist-info/RECORD
