Metadata-Version: 2.1
Name: hgcroc-toa-simulator
Version: 0.4.5
Summary: Application that simulates the two-stage TDC implemented in the HGCROCv3 ASIC
Author: Alexander Becker
Author-email: a.becker@cern.ch
License: GPL3
Keywords: simulation,electronics,science
Classifier: Programming Language :: Python :: 3
Classifier: License :: OSI Approved :: GNU General Public License v3 (GPLv3)
Classifier: Operating System :: POSIX :: Linux
Classifier: Environment :: Console
License-File: LICENSE.rst
Requires-Dist: numpy
Requires-Dist: matplotlib
Requires-Dist: PyQt6
Requires-Dist: click
Requires-Dist: pyyaml
